Workbook

Sheet DCF Forecast
A1: Metric | B1: 2026 Actual | C1: 2027 Forecast | D1: 2028 Forecast | E1: 2029 Forecast | F1: 2030 Forecast | G1: 2031 Forecast
A2: Revenue Growth | B2: ='Historical Financials'!D7 -> 0.032604053 | C2: 0.02 | D2: 0.025 | E2: 0.027 | F2: 0.03 | G2: 0.03
A3: Revenue | B3: ='Historical Financials'!D2 -> 87032 | C3: =B3*(1+C2) -> 88772.64 | D3: =C3*(1+D2) -> 90991.956 | E3: =D3*(1+E2) -> 93448.739 | F3: =E3*(1+F2) -> 96252.201 | G3: =F3*(1+G2) -> 99139.767
A4: Operating Margin | B4: ='Historical Financials'!D8 -> 0.22690505 | C4: 0.23 | D4: 0.232 | E4: 0.234 | F4: 0.235 | G4: 0.235
A5: Operating Income (EBIT) | B5: ='Historical Financials'!D3 -> 19748 | C5: =C3*C4 -> 20417.707 | D5: =D3*D4 -> 21110.134 | E5: =E3*E4 -> 21867.005 | F5: =F3*F4 -> 22619.267 | G5: =G3*G4 -> 23297.845
A6: Tax Rate | B6: ='Historical Financials'!D9 -> 0.20773421 | C6: 0.21 | D6: 0.21 | E6: 0.21 | F6: 0.21 | G6: 0.21
A7: EBIT After Tax | B7: =B5*(1-B6) -> 15645.665 | C7: =C5*(1-C6) -> 16129.989 | D7: =D5*(1-D6) -> 16677.006 | E7: =E5*(1-E6) -> 17274.934 | F7: =F5*(1-F6) -> 17869.221 | G7: =G5*(1-G6) -> 18405.298
A8: D&A / Revenue | B8: ='Historical Financials'!D25 -> 0.036308484 | C8: 0.035 | D8: 0.035 | E8: 0.035 | F8: 0.035 | G8: 0.035
A9: Depreciation & Amortization | B9: ='Historical Financials'!D11 -> 3160 | C9: =C3*C8 -> 3107.0424 | D9: =D3*D8 -> 3184.7185 | E9: =E3*E8 -> 3270.7059 | F9: =F3*F8 -> 3368.827 | G9: =G3*G8 -> 3469.8918
A10: CapEx / Revenue | B10: ='Historical Financials'!D26 -> 0.050659528 | C10: 0.05 | D10: 0.05 | E10: 0.048 | F10: 0.047 | G10: 0.045
A11: Capital Expenditures | B11: ='Historical Financials'!D12 -> 4409 | C11: =C3*C10 -> 4438.632 | D11: =D3*D10 -> 4549.5978 | E11: =E3*E10 -> 4485.5395 | F11: =F3*F10 -> 4523.8534 | G11: =G3*G10 -> 4461.2895
A12: Net Working Capital | B12: ='Historical Financials'!D20 -> -11131 | C12: =C3*($B$12/$B$3) -> -11353.62 | D12: =D3*($B$12/$B$3) -> -11637.46 | E12: =E3*($B$12/$B$3) -> -11951.672 | F12: =F3*($B$12/$B$3) -> -12310.222 | G12: =G3*($B$12/$B$3) -> -12679.529
A13: Change in NWC | B13: ='Historical Financials'!D21 -> -422 | C13: =C12-B12 -> -222.62 | D13: =D12-C12 -> -283.8405 | E13: =E12-D12 -> -314.21143 | F13: =F12-E12 -> -358.55016 | G13: =G12-F12 -> -369.30666
A14: Free Cash Flow to Firm (FCFF) | B14: =B7+B9-B11-B13 -> 14818.665 | C14: =C7+C9-C11-C13 -> 15021.019 | D14: =D7+D9-D11-D13 -> 15595.967 | E14: =E7+E9-E11-E13 -> 16374.312 | F14: =F7+F9-F11-F13 -> 17072.745 | G14: =G7+G9-G11-G13 -> 17783.207

Sheet DCF Valuation
A1: WACC CALCULATION | B1: Value
A2: Risk-Free Rate (Rf) | B2: 0.051 | D2: 2025 Total Debt | E2: 34508
A3: Equity Beta | B3: 0.3843 | D3: 2026 Interest Expense | E3: 877
A4: Equity Risk Premium (ERP) | B4: 0.042 | D4: Average Debt | E4: =AVERAGE(E2,B8) -> 34323
A5: Cost of Equity (Re) | B5: =B2+B3*B4 -> 0.0671406
A6: Short-Term Debt | B6: 11296 | D6: Share Price (16 October 2026) | E6: 159.35
A7: Long-Term Debt | B7: 22842 | D7: Shares Outstanding (millions) | E7: 2323.859
A8: Total Debt | B8: =SUM(B6:B7) -> 34138
A9: Cost of Debt (Rd) | B9: =E13 -> 0.0567 | D9: Preferred Conversion Dilution Effect (millions) | E9: 68.3
A10: Tax Rate | B10: 0.21 | D10: Other Dilutive Securities (millions) | E10: 20.5
A11: Market Capitalization (E) | B11: =E6*E7 -> 370306.93 | D11: Estimated Diluted Shares (millions) | E11: =E7+E9+E10 -> 2412.659
A12: Equity Weight | B12: =B11/(B8+B11) -> 0.91559296 | D12: Reported Average Debt Interest Rate (2026) | E12: 0.033
A13: Debt Weight | B13: =B8/(B8+B11) -> 0.084407041 | D13: AA Corporate Bond Yield (15 October 2026) | E13: 0.0567
A14: WACC | B14: =B12*B5+B13*B9*(1-B10) -> 0.065254305
A17: Metric | B17: 2027 | C17: 2028 | D17: 2029 | E17: 2030 | F17: 2031
A18: Year (t) | B18: 1 | C18: 2 | D18: 3 | E18: 4 | F18: 5
A19: Forecast FCFF | B19: ='DCF Forecast'!C14 -> 15021.019 | C19: ='DCF Forecast'!D14 -> 15595.967 | D19: ='DCF Forecast'!E14 -> 16374.312 | E19: ='DCF Forecast'!F14 -> 17072.745 | F19: ='DCF Forecast'!G14 -> 17783.207
A20: Discount Factor | B20: =1/(1+$B$14)^B18 -> 0.93874298 | C20: =1/(1+$B$14)^C18 -> 0.88123838 | D20: =1/(1+$B$14)^D18 -> 0.82725634 | E20: =1/(1+$B$14)^E18 -> 0.77658108 | F20: =1/(1+$B$14)^F18 -> 0.72901004
A21: Present Value of FCFF | B21: =B19*B20 -> 14100.876 | C21: =C19*C20 -> 13743.765 | D21: =D19*D20 -> 13545.753 | E21: =E19*E20 -> 13258.371 | F21: =F19*F20 -> 12964.136
A23: PV of Forecast FCFF | B23: =SUM(B21:F21) -> 67612.901
A25: Terminal Growth Rate (g) | B25: 0.025
A26: Terminal Value (2031) | B26: =F19*(1+B25)/(B14-B25) -> 452815.84
A27: PV of Terminal Value | B27: =B26*F20 -> 330107.29
A28: Enterprise Value (EV) | B28: =B23+B27 -> 397720.19
A30: Total Debt | B30: =B8 -> 34138
A31: Cash and Cash Equivalents | B31: 9942
A32: Net Debt | B32: =B30-B31 -> 24196
A33: Noncontrolling Interest | B33: 230
A34: Preferred Stock (Book Value — Reference) | B34: 756
A35: Provisional Equity Value (BeforePreferredAdj) | B35: =B28-B32-B33 -> 373294.19
A37: Provisional Value per Share | B37: =B35/E11 -> 154.72315

Sheet Historical Financials
A1: Metric | B1: 2024 | C1: 2025 | D1: 2026 | E1: 2023 (NWC Reference)
A2: Revenue | B2: 84039 | C2: 84284 | D2: 87032
A3: Operating Income (EBIT) | B3: 18545 | C3: 20451 | D3: 19748
A4: Income Taxes | B4: 3787 | C4: 4102 | D4: 4233
A5: Earnings Before Taxes | B5: 18761 | C5: 20167 | D5: 20377
A7: Revenue Growth | C7: =(C2/B2)-1 -> 0.0029153131 | D7: =(D2/C2)-1 -> 0.032604053
A8: Operating Margin | B8: =B3/B2 -> 0.22067136 | C8: =C3/C2 -> 0.24264392 | D8: =D3/D2 -> 0.22690505
A9: Effective Tax Rate | B9: =B4/B5 -> 0.20185491 | C9: =C4/C5 -> 0.2034016 | D9: =D4/D5 -> 0.20773421
A11: Depreciation & Amortization | B11: 2896 | C11: 2847 | D11: 3160
A12: Capital Expenditures (CapEx) | B12: 3322 | C12: 3773 | D12: 4409
A14: Accounts Receivable | B14: 6118 | C14: 6185 | D14: 6056 | E14: 5471
A15: Inventories | B15: 7016 | C15: 7551 | D15: 8170 | E15: 7073
A16: Other Current Assets | B16: 2095 | C16: 2100 | D16: 2040 | E16: 1858
A17: Accounts Payable | B17: 15364 | C17: 15227 | D17: 16306 | E17: 14598
A18: Accrued & Other Liabilities | B18: 11073 | C18: 11318 | D18: 11091 | E18: 10929
A20: Net Working Capital (NWC) | B20: =SUM(B14:B16)-SUM(B17:B18) -> -11208 | C20: =SUM(C14:C16)-SUM(C17:C18) -> -10709 | D20: =SUM(D14:D16)-SUM(D17:D18) -> -11131 | E20: =SUM(E14:E16)-SUM(E17:E18) -> -11125
A21: Change in NWC | B21: =B20-E20 -> -83 | C21: =C20-B20 -> 499 | D21: =D20-C20 -> -422
A23: Free Cash Flow to Firm (FCFF) | B23: =B3*(1-B9)+B11-B12-B21 -> 14458.601 | C23: =C3*(1-C9)+C11-C12-C21 -> 14866.234 | D23: =D3*(1-D9)+D11-D12-D21 -> 14818.665
A25: D&A / Revenue | B25: =B11/B2 -> 0.034460191 | C25: =C11/C2 -> 0.033778653 | D25: =D11/D2 -> 0.036308484
A26: CapEx / Revenue | B26: =B12/B2 -> 0.039529266 | C26: =C12/C2 -> 0.044765317 | D26: =D12/D2 -> 0.050659528

Sheet Sensitivity Analysis
A1: Sensitivity Analysis — Value per Share (USD)
A3: WACC / Terminal Growth | B3: 0.015 | C3: 0.02 | D3: 0.025 | E3: 0.03 | F3: 0.035
A4: ='DCF Valuation'!B14-1% -> 0.055254305 | B4: =(SUMPRODUCT('DCF Valuation'!$B$19:$F$19/(1+$A4)^'DCF Valuation'!$B$18:$F$18)+('DCF Valuation'!$F$19*(1+B$3)/($A4-B$3))/(1+$A4)^5-'DCF Valuation'!$B$32-'DCF Valuation'!$B$33)/'DCF Valuation'!$E$11 -> 160.72656 | C4: =(SUMPRODUCT('DCF Valuation'!$B$19:$F$19/(1+$A4)^'DCF Valuation'!$B$18:$F$18)+('DCF Valuation'!$F$19*(1+C$3)/($A4-C$3))/(1+$A4)^5-'DCF Valuation'!$B$32-'DCF Valuation'!$B$33)/'DCF Valuation'!$E$11 -> 181.66918 | D4: =(SUMPRODUCT('DCF Valuation'!$B$19:$F$19/(1+$A4)^'DCF Valuation'!$B$18:$F$18)+('DCF Valuation'!$F$19*(1+D$3)/($A4-D$3))/(1+$A4)^5-'DCF Valuation'!$B$32-'DCF Valuation'!$B$33)/'DCF Valuation'!$E$11 -> 209.53401 | E4: =(SUMPRODUCT('DCF Valuation'!$B$19:$F$19/(1+$A4)^'DCF Valuation'!$B$18:$F$18)+('DCF Valuation'!$F$19*(1+E$3)/($A4-E$3))/(1+$A4)^5-'DCF Valuation'!$B$32-'DCF Valuation'!$B$33)/'DCF Valuation'!$E$11 -> 248.43252 | F4: =(SUMPRODUCT('DCF Valuation'!$B$19:$F$19/(1+$A4)^'DCF Valuation'!$B$18:$F$18)+('DCF Valuation'!$F$19*(1+F$3)/($A4-F$3))/(1+$A4)^5-'DCF Valuation'!$B$32-'DCF Valuation'!$B$33)/'DCF Valuation'!$E$11 -> 306.53609
A5: ='DCF Valuation'!B14-0.5% -> 0.060254305 | B5: =(SUMPRODUCT('DCF Valuation'!$B$19:$F$19/(1+$A5)^'DCF Valuation'!$B$18:$F$18)+('DCF Valuation'!$F$19*(1+B$3)/($A5-B$3))/(1+$A5)^5-'DCF Valuation'!$B$32-'DCF Valuation'!$B$33)/'DCF Valuation'!$E$11 -> 141.68083 | C5: =(SUMPRODUCT('DCF Valuation'!$B$19:$F$19/(1+$A5)^'DCF Valuation'!$B$18:$F$18)+('DCF Valuation'!$F$19*(1+C$3)/($A5-C$3))/(1+$A5)^5-'DCF Valuation'!$B$32-'DCF Valuation'!$B$33)/'DCF Valuation'!$E$11 -> 157.69011 | D5: =(SUMPRODUCT('DCF Valuation'!$B$19:$F$19/(1+$A5)^'DCF Valuation'!$B$18:$F$18)+('DCF Valuation'!$F$19*(1+D$3)/($A5-D$3))/(1+$A5)^5-'DCF Valuation'!$B$32-'DCF Valuation'!$B$33)/'DCF Valuation'!$E$11 -> 178.24047 | E5: =(SUMPRODUCT('DCF Valuation'!$B$19:$F$19/(1+$A5)^'DCF Valuation'!$B$18:$F$18)+('DCF Valuation'!$F$19*(1+E$3)/($A5-E$3))/(1+$A5)^5-'DCF Valuation'!$B$32-'DCF Valuation'!$B$33)/'DCF Valuation'!$E$11 -> 205.58337 | F5: =(SUMPRODUCT('DCF Valuation'!$B$19:$F$19/(1+$A5)^'DCF Valuation'!$B$18:$F$18)+('DCF Valuation'!$F$19*(1+F$3)/($A5-F$3))/(1+$A5)^5-'DCF Valuation'!$B$32-'DCF Valuation'!$B$33)/'DCF Valuation'!$E$11 -> 243.7533
A6: ='DCF Valuation'!B14 -> 0.065254305 | B6: =(SUMPRODUCT('DCF Valuation'!$B$19:$F$19/(1+$A6)^'DCF Valuation'!$B$18:$F$18)+('DCF Valuation'!$F$19*(1+B$3)/($A6-B$3))/(1+$A6)^5-'DCF Valuation'!$B$32-'DCF Valuation'!$B$33)/'DCF Valuation'!$E$11 -> 126.42778 | C6: =(SUMPRODUCT('DCF Valuation'!$B$19:$F$19/(1+$A6)^'DCF Valuation'!$B$18:$F$18)+('DCF Valuation'!$F$19*(1+C$3)/($A6-C$3))/(1+$A6)^5-'DCF Valuation'!$B$32-'DCF Valuation'!$B$33)/'DCF Valuation'!$E$11 -> 139.01233 | D6: =(SUMPRODUCT('DCF Valuation'!$B$19:$F$19/(1+$A6)^'DCF Valuation'!$B$18:$F$18)+('DCF Valuation'!$F$19*(1+D$3)/($A6-D$3))/(1+$A6)^5-'DCF Valuation'!$B$32-'DCF Valuation'!$B$33)/'DCF Valuation'!$E$11 -> 154.72315 | E6: =(SUMPRODUCT('DCF Valuation'!$B$19:$F$19/(1+$A6)^'DCF Valuation'!$B$18:$F$18)+('DCF Valuation'!$F$19*(1+E$3)/($A6-E$3))/(1+$A6)^5-'DCF Valuation'!$B$32-'DCF Valuation'!$B$33)/'DCF Valuation'!$E$11 -> 174.89039 | F6: =(SUMPRODUCT('DCF Valuation'!$B$19:$F$19/(1+$A6)^'DCF Valuation'!$B$18:$F$18)+('DCF Valuation'!$F$19*(1+F$3)/($A6-F$3))/(1+$A6)^5-'DCF Valuation'!$B$32-'DCF Valuation'!$B$33)/'DCF Valuation'!$E$11 -> 201.72353
A7: ='DCF Valuation'!B14+0.5% -> 0.070254305 | B7: =(SUMPRODUCT('DCF Valuation'!$B$19:$F$19/(1+$A7)^'DCF Valuation'!$B$18:$F$18)+('DCF Valuation'!$F$19*(1+B$3)/($A7-B$3))/(1+$A7)^5-'DCF Valuation'!$B$32-'DCF Valuation'!$B$33)/'DCF Valuation'!$E$11 -> 113.93774 | C7: =(SUMPRODUCT('DCF Valuation'!$B$19:$F$19/(1+$A7)^'DCF Valuation'!$B$18:$F$18)+('DCF Valuation'!$F$19*(1+C$3)/($A7-C$3))/(1+$A7)^5-'DCF Valuation'!$B$32-'DCF Valuation'!$B$33)/'DCF Valuation'!$E$11 -> 124.05346 | D7: =(SUMPRODUCT('DCF Valuation'!$B$19:$F$19/(1+$A7)^'DCF Valuation'!$B$18:$F$18)+('DCF Valuation'!$F$19*(1+D$3)/($A7-D$3))/(1+$A7)^5-'DCF Valuation'!$B$32-'DCF Valuation'!$B$33)/'DCF Valuation'!$E$11 -> 136.40449 | E7: =(SUMPRODUCT('DCF Valuation'!$B$19:$F$19/(1+$A7)^'DCF Valuation'!$B$18:$F$18)+('DCF Valuation'!$F$19*(1+E$3)/($A7-E$3))/(1+$A7)^5-'DCF Valuation'!$B$32-'DCF Valuation'!$B$33)/'DCF Valuation'!$E$11 -> 151.82376 | F7: =(SUMPRODUCT('DCF Valuation'!$B$19:$F$19/(1+$A7)^'DCF Valuation'!$B$18:$F$18)+('DCF Valuation'!$F$19*(1+F$3)/($A7-F$3))/(1+$A7)^5-'DCF Valuation'!$B$32-'DCF Valuation'!$B$33)/'DCF Valuation'!$E$11 -> 171.61677
A8: ='DCF Valuation'!B14+1% -> 0.075254305 | B8: =(SUMPRODUCT('DCF Valuation'!$B$19:$F$19/(1+$A8)^'DCF Valuation'!$B$18:$F$18)+('DCF Valuation'!$F$19*(1+B$3)/($A8-B$3))/(1+$A8)^5-'DCF Valuation'!$B$32-'DCF Valuation'!$B$33)/'DCF Valuation'!$E$11 -> 103.52282 | C8: =(SUMPRODUCT('DCF Valuation'!$B$19:$F$19/(1+$A8)^'DCF Valuation'!$B$18:$F$18)+('DCF Valuation'!$F$19*(1+C$3)/($A8-C$3))/(1+$A8)^5-'DCF Valuation'!$B$32-'DCF Valuation'!$B$33)/'DCF Valuation'!$E$11 -> 111.80387 | D8: =(SUMPRODUCT('DCF Valuation'!$B$19:$F$19/(1+$A8)^'DCF Valuation'!$B$18:$F$18)+('DCF Valuation'!$F$19*(1+D$3)/($A8-D$3))/(1+$A8)^5-'DCF Valuation'!$B$32-'DCF Valuation'!$B$33)/'DCF Valuation'!$E$11 -> 121.73274 | E8: =(SUMPRODUCT('DCF Valuation'!$B$19:$F$19/(1+$A8)^'DCF Valuation'!$B$18:$F$18)+('DCF Valuation'!$F$19*(1+E$3)/($A8-E$3))/(1+$A8)^5-'DCF Valuation'!$B$32-'DCF Valuation'!$B$33)/'DCF Valuation'!$E$11 -> 133.85563 | F8: =(SUMPRODUCT('DCF Valuation'!$B$19:$F$19/(1+$A8)^'DCF Valuation'!$B$18:$F$18)+('DCF Valuation'!$F$19*(1+F$3)/($A8-F$3))/(1+$A8)^5-'DCF Valuation'!$B$32-'DCF Valuation'!$B$33)/'DCF Valuation'!$E$11 -> 148.9901

Sheet Reverse DCF
A1: REVERSE DCF — P&G | B1: Value
A2: Market Share Price (USD) | B2: ='DCF Valuation'!E6 -> 159.35
A3: WACC | B3: ='DCF Valuation'!B14 -> 0.065254305
A4: Terminal Growth Rate (g) | B4: ='DCF Valuation'!B25 -> 0.025
A5: Estimated Diluted Shares (millions) | B5: ='DCF Valuation'!E11 -> 2412.659
A6: Net Debt (USD millions) | B6: ='DCF Valuation'!B32 -> 24196
A7: Noncontrolling Interest (USD millions) | B7: ='DCF Valuation'!B33 -> 230
A8: Reverse DCF Implied Annual Revenue Growth | B8: 0.031942
A9: Reverse DCF Share Value | B9: =(SUM(C28:G28)+(G26*(1+B4)/(B3-B4))/(1+B3)^5-B6-B7)/B5 -> 159.35036
A10: Difference from Market Price | B10: =B9-B2 -> 0.00035983134
A12: Metric | B12: 2026 Actual | C12: 2027 Forecast | D12: 2028 Forecast | E12: 2029 Forecast | F12: 2030 Forecast | G12: 2031 Forecast
A13: Revenue Growth | C13: =$B$8 -> 0.031942 | D13: =$B$8 -> 0.031942 | E13: =$B$8 -> 0.031942 | F13: =$B$8 -> 0.031942 | G13: =$B$8 -> 0.031942
A14: Revenue | B14: ='DCF Forecast'!B3 -> 87032 | C14: =B14*(1+C13) -> 89811.976 | D14: =C14*(1+D13) -> 92680.75 | E14: =D14*(1+E13) -> 95641.159 | F14: =E14*(1+F13) -> 98696.129 | G14: =F14*(1+G13) -> 101848.68
A15: Operating Margin | C15: ='DCF Forecast'!C4 -> 0.23 | D15: ='DCF Forecast'!D4 -> 0.232 | E15: ='DCF Forecast'!E4 -> 0.234 | F15: ='DCF Forecast'!F4 -> 0.235 | G15: ='DCF Forecast'!G4 -> 0.235
A16: EBIT | C16: =C14*C15 -> 20656.755 | D16: =D14*D15 -> 21501.934 | E16: =E14*E15 -> 22380.031 | F16: =F14*F15 -> 23193.59 | G16: =G14*G15 -> 23934.44
A17: Tax Rate | C17: ='DCF Forecast'!C6 -> 0.21 | D17: ='DCF Forecast'!D6 -> 0.21 | E17: ='DCF Forecast'!E6 -> 0.21 | F17: ='DCF Forecast'!F6 -> 0.21 | G17: ='DCF Forecast'!G6 -> 0.21
A18: EBIT After Tax | C18: =C16*(1-C17) -> 16318.836 | D18: =D16*(1-D17) -> 16986.528 | E18: =E16*(1-E17) -> 17680.225 | F18: =F16*(1-F17) -> 18322.936 | G18: =G16*(1-G17) -> 18908.208
A19: D&A / Revenue | C19: ='DCF Forecast'!C8 -> 0.035 | D19: ='DCF Forecast'!D8 -> 0.035 | E19: ='DCF Forecast'!E8 -> 0.035 | F19: ='DCF Forecast'!F8 -> 0.035 | G19: ='DCF Forecast'!G8 -> 0.035
A20: Depreciation & Amortization | C20: =C14*C19 -> 3143.4192 | D20: =D14*D19 -> 3243.8263 | E20: =E14*E19 -> 3347.4406 | F20: =F14*F19 -> 3454.3645 | G20: =G14*G19 -> 3564.7038
A21: CapEx / Revenue | C21: ='DCF Forecast'!C10 -> 0.05 | D21: ='DCF Forecast'!D10 -> 0.05 | E21: ='DCF Forecast'!E10 -> 0.048 | F21: ='DCF Forecast'!F10 -> 0.047 | G21: ='DCF Forecast'!G10 -> 0.045
A22: Capital Expenditures | C22: =C14*C21 -> 4490.5988 | D22: =D14*D21 -> 4634.0375 | E22: =E14*E21 -> 4590.7756 | F22: =F14*F21 -> 4638.718 | G22: =G14*G21 -> 4583.1906
A23: NWC / Revenue | B23: ='DCF Forecast'!B12/'DCF Forecast'!B3 -> -0.12789549 | C23: =$B$23 -> -0.12789549 | D23: =$B$23 -> -0.12789549 | E23: =$B$23 -> -0.12789549 | F23: =$B$23 -> -0.12789549 | G23: =$B$23 -> -0.12789549
A24: Net Working Capital | B24: ='DCF Forecast'!B12 -> -11131 | C24: =C14*C23 -> -11486.546 | D24: =D14*D23 -> -11853.45 | E24: =E14*E23 -> -12232.073 | F24: =F14*F23 -> -12622.789 | G24: =G14*G23 -> -13025.987
A25: Change in NWC | C25: =C24-B24 -> -355.5464 | D25: =D24-C24 -> -366.90327 | E25: =E24-D24 -> -378.62289 | F25: =F24-E24 -> -390.71686 | G25: =G24-F24 -> -403.19714
A26: FCFF | C26: =C18+C20-C22-C25 -> 15327.203 | D26: =D18+D20-D22-D25 -> 15963.22 | E26: =E18+E20-E22-E25 -> 16815.512 | F26: =F18+F20-F22-F25 -> 17529.3 | G26: =G18+G20-G22-G25 -> 18292.918
A27: Year (t) | C27: 1 | D27: 2 | E27: 3 | F27: 4 | G27: 5
A28: Present Value of FCFF | C28: =C26/(1+$B$3)^C27 -> 14388.304 | D28: =D26/(1+$B$3)^D27 -> 14067.402 | E28: =E26/(1+$B$3)^E27 -> 13910.739 | F28: =F26/(1+$B$3)^F27 -> 13612.922 | G28: =G26/(1+$B$3)^G27 -> 13335.721

Sheet Consensus Comparison
A1: Metric | B1: 2027 | C1: 2028
A2: Our DCF Revenue Growth | B2: 0.02 | C2: 0.025
A3: Analyst Consensus (Zacks) | B3: 0.0177 | C3: 0.0278
A4: P&G Management Guidance (Range) | B4: 1%–3% | C4: ---
A5: Reverse DCF Implied Annual Growth | B5: ='Reverse DCF'!B8 -> 0.031942 | C5: ='Reverse DCF'!B8 -> 0.031942
A7: Sources & Methodology Notes
A8: DCF Forecast: Internal model assumptions (FY2027–FY2028).
A9: Management Guidance: P&G FY2027 outlook published 29 July 2026.
A10: Reverse DCF: Implied constant annual revenue growth under the model assumptions.
A11: Valuation Date: 16 October 2026. Analyst estimates are used as subsequent benchmarks.
A12: Analyst Consensus: Zacks sales estimates; publication date not independently verified.

Sheet Valuation Chart
A1: Metric | B1: Price per Share (USD)
A2: DCF Fair Value | B2: ='DCF Valuation'!B37 -> 154.72315
A3: Market Price | B3: ='DCF Valuation'!E6 -> 159.35
